setup.py
roadtools/roadtune/__init__.py
roadtune.egg-info/PKG-INFO
roadtune.egg-info/SOURCES.txt
roadtune.egg-info/dependency_links.txt
roadtune.egg-info/entry_points.txt
roadtune.egg-info/not-zip-safe
roadtune.egg-info/requires.txt
roadtune.egg-info/top_level.txt